openminds/__init__.py
openminds/base.py
openminds/collection.py
openminds/properties.py
openminds/registry.py
openminds/latest/__init__.py
openminds/latest/chemicals/__init__.py
openminds/latest/chemicals/amount_of_chemical.py
openminds/latest/chemicals/chemical_mixture.py
openminds/latest/chemicals/chemical_substance.py
openminds/latest/chemicals/product_source.py
openminds/latest/computation/__init__.py
openminds/latest/computation/data_analysis.py
openminds/latest/computation/data_copy.py
openminds/latest/computation/environment.py
openminds/latest/computation/generic_computation.py
openminds/latest/computation/hardware_system.py
openminds/latest/computation/launch_configuration.py
openminds/latest/computation/local_file.py
openminds/latest/computation/model_validation.py
openminds/latest/computation/optimization.py
openminds/latest/computation/simulation.py
openminds/latest/computation/software_agent.py
openminds/latest/computation/validation_test.py
openminds/latest/computation/validation_test_version.py
openminds/latest/computation/visualization.py
openminds/latest/computation/workflow_execution.py
openminds/latest/computation/workflow_recipe.py
openminds/latest/computation/workflow_recipe_version.py
openminds/latest/controlled_terms/__init__.py
openminds/latest/controlled_terms/action_status_type.py
openminds/latest/controlled_terms/age_category.py
openminds/latest/controlled_terms/analysis_technique.py
openminds/latest/controlled_terms/anatomical_axes_orientation.py
openminds/latest/controlled_terms/anatomical_identification_type.py
openminds/latest/controlled_terms/anatomical_plane.py
openminds/latest/controlled_terms/annotation_criteria_type.py
openminds/latest/controlled_terms/annotation_type.py
openminds/latest/controlled_terms/atlas_type.py
openminds/latest/controlled_terms/auditory_stimulus_type.py
openminds/latest/controlled_terms/biological_order.py
openminds/latest/controlled_terms/biological_process.py
openminds-0.4.0.dist-info/licenses/LICENSE
openminds-0.4.0.dist-info/METADATA
openminds-0.4.0.dist-info/WHEEL
openminds-0.4.0.dist-info/top_level.txt
openminds-0.4.0.dist-info/RECORD
