Metadata-Version: 2.4
Name: openMINDS
Version: 0.4.0
Summary: Python library for interacting with openMINDS metadata schemas
Author: Louisa Köhnen, Raphaël Gazzotti
Author-email: "Andrew P. Davison" <andrew.davison@cnrs.fr>, Lyuba Zehl <lyuba.zehl@ebrains.eu>, Peyman Najafi <peyman.najafi@cnrs.fr>
License-Expression: MIT
Project-URL: Homepage, https://github.com/openMetadataInitiative/openMINDS_Python
Keywords: openMINDS,Open Metadata Initiative,metadata
Classifier: Development Status :: 4 - Beta
Classifier: Intended Audience :: Science/Research
Classifier: Topic :: Scientific/Engineering
Classifier: Programming Language :: Python :: 3
Requires-Python: >=3.9
License-File: LICENSE
Requires-Dist: rfc3987
Provides-Extra: dev
Requires-Dist: pytest; extra == "dev"
Requires-Dist: pytest-cov; extra == "dev"
Requires-Dist: pytest-mock; extra == "dev"
Requires-Dist: coverage; extra == "dev"
Requires-Dist: build; extra == "dev"
Requires-Dist: setuptools; extra == "dev"
Requires-Dist: wheel; extra == "dev"
Requires-Dist: sphinx; extra == "dev"
Requires-Dist: ruff; extra == "dev"
Requires-Dist: twine; extra == "dev"
Dynamic: license-file
